<?xml version="1.0" encoding="UTF-8" ?>
<!DOCTYPE struts PUBLIC
        "-//Apache Software Foundation//DTD Struts Configuration 2.3//EN"
        "http://struts.apache.org/dtds/struts-2.3.dtd">

<struts>
    <!-- 修改动态方法的调用,true 动态方法，false 非动态方法 -->
    <constant name="struts.enable.DynamicMethodInvocation" value="true"/>

    <package name="default" namespace="/" extends="struts-default">
        <action name="userAction!*" class="userAction" method="{1}">
            <result name="info">/WEB-INF/views/user/info.jsp</result>

            <result name="list">/WEB-INF/views/user/list.jsp</result>
            <result name="save">/WEB-INF/views/user/form.jsp</result>
            <result name="edit">/WEB-INF/views/user/edit.jsp</result>
        </action>
    </package>
</struts>